beautifuldict/__init__.py
beautifuldict/baseconfig.py
beautifuldict/test/__init__.py
beautifuldict/test/test_baseconfig.py
beautifuldict-0.1.1.dist-info/AUTHORS.rst
beautifuldict-0.1.1.dist-info/LICENSE.txt
beautifuldict-0.1.1.dist-info/METADATA
beautifuldict-0.1.1.dist-info/WHEEL
beautifuldict-0.1.1.dist-info/top_level.txt
beautifuldict-0.1.1.dist-info/RECORD
