Metadata-Version: 2.1
Name: beautifuldict
Version: 0.1.1
Summary: Utils for managing configurations
Home-page: https://github.com/icane/beautifuldict.git
Author: Servicio de Informática y Banco de Datos
Author-email: sibd@cantabria.es
License: Apache License 2.0
Keywords: configuration,utils
Platform: UNKNOWN
Classifier: Development Status :: 4 - Beta
Classifier: Environment :: Console
Classifier: Intended Audience :: Developers
Classifier: License :: OSI Approved :: Apache Software License
Classifier: Operating System :: MacOS :: MacOS X
Classifier: Operating System :: Microsoft :: Windows
Classifier: Operating System :: POSIX
Classifier: Programming Language :: Python
Classifier: Topic :: Software Development :: Libraries
